django_werobot.py
setup.cfg
setup.py
Django_WeRoBot.egg-info/PKG-INFO
Django_WeRoBot.egg-info/SOURCES.txt
Django_WeRoBot.egg-info/dependency_links.txt
Django_WeRoBot.egg-info/not-zip-safe
Django_WeRoBot.egg-info/requires.txt
Django_WeRoBot.egg-info/top_level.txt